pyforever/__init__.py
pyforever/__main__.py
pyforever/__version__.py
pyforever/watchers.py
pyforever-0.2.1.dist-info/LICENSE.txt
pyforever-0.2.1.dist-info/METADATA
pyforever-0.2.1.dist-info/WHEEL
pyforever-0.2.1.dist-info/entry_points.txt
pyforever-0.2.1.dist-info/top_level.txt
pyforever-0.2.1.dist-info/RECORD
